client/__init__.py
client/client.py
client/client/__init__.py
client/client/add_contact.py
client/client/database.py
client/client/del_contact.py
client/client/main_window.py
client/client/main_window_converted.py
client/client/start_dialog.py
client/client/transport.py
client/common/__init__.py
client/common/decorators.py
client/common/descriptors.py
client/common/errors.py
client/common/metaclasses.py
client/common/utils.py
client/common/variables.py
client/logs/__init__.py
client/logs/client_log_config.py
client/logs/server_log_config.py
client/unit_tests/__init__.py
client/unit_tests/test_client.py
client/unit_tests/test_server.py
client/unit_tests/test_utils.py
me55enger_client-0.0.2.dist-info/METADATA
me55enger_client-0.0.2.dist-info/WHEEL
me55enger_client-0.0.2.dist-info/top_level.txt
me55enger_client-0.0.2.dist-info/RECORD
